LICENSE
MANIFEST.in
README.md
setup.py
django_webhooks2.egg-info/PKG-INFO
django_webhooks2.egg-info/SOURCES.txt
django_webhooks2.egg-info/dependency_links.txt
django_webhooks2.egg-info/requires.txt
django_webhooks2.egg-info/top_level.txt
webhooks/__init__.py
webhooks/admin.py
webhooks/models.py
webhooks/registry.py
webhooks/utils.py
webhooks/migrations/0001_initial.py
webhooks/migrations/__init__.py