Metadata-Version: 1.0
Name: django-webhooks2
Version: 0.1.0
Summary: Simple webhooks for Django
Home-page: https://github.com/cbmi/django-webhooks/
Author: Byron Ruth
Author-email: b@devel.io
License: BSD
Keywords: webhooks events callbacks
Platform: UNKNOWN
Classifier: Development Status :: 4 - Beta
Classifier: License :: OSI Approved :: BSD License
Classifier: Programming Language :: Python :: 2.6
Classifier: Programming Language :: Python :: 2.7
Classifier: Framework :: Django
Classifier: Topic :: Internet :: WWW/HTTP
Classifier: Intended Audience :: Developers
